Penvis/__init__.py
Penvis/add_num.py
Penvis/config.py
Penvis/data_format_converter.py
Penvis/function_orchestration_module.py
Penvis/function_planning_module.py
Penvis/intent_understanding_module.py
Penvis/memory_module.py
Penvis/测试.py
PenVis-0.0.3.dist-info/METADATA
PenVis-0.0.3.dist-info/WHEEL
PenVis-0.0.3.dist-info/license.txt.txt
PenVis-0.0.3.dist-info/top_level.txt
PenVis-0.0.3.dist-info/RECORD
