Metadata-Version: 2.1
Name: PenVis
Version: 0.0.3
Summary: An angent framework
Author: Xunli
Author-email: chenying1211@stu.pku.edu.cn
Classifier: Programming Language :: Python :: 3
Classifier: License :: OSI Approved :: MIT License
Classifier: Operating System :: OS Independent
Requires-Python: >=3.6
License-File: license.txt.txt
